{
  "source": "yfinance",
  "fetched_at_utc": "2026-06-16T17:20:09.110873+00:00",
  "fetched_at_lima": "2026-06-16T12:20:09.110873-05:00",
  "interval": "15m",
  "period": "5d",
  "count": 12,
  "ok_count": 12,
  "error_count": 0,
  "data": [
    {
      "symbol": "USDPEN=X",
      "name": "USD/PEN",
      "category": "FX",
      "price": 3.3717,
      "previous_close": 3.331346,
      "change": 0.040354,
      "change_pct": 1.2113,
      "direction": "up",
      "price_time": "2026-06-16T13:15:00-04:00",
      "sparkline": [
        3.4042,
        3.4043,
        3.4042,
        3.4043,
        3.4043,
        3.4041,
        3.4042,
        3.4041,
        3.4043,
        3.4043,
        3.4059,
        3.4061,
        3.4062,
        3.4061,
        3.4059,
        3.4051,
        3.4058,
        3.4061,
        3.3798,
        3.3781,
        3.376,
        3.37,
        3.3726,
        3.3753,
        3.3741,
        3.3731,
        3.3721,
        3.3726,
        3.3721,
        3.3715,
        3.3737,
        3.3717
      ],
      "status": "ok"
    },
    {
      "symbol": "EURUSD=X",
      "name": "EUR/USD",
      "category": "FX",
      "price": 1.161575,
      "previous_close": 1.160308,
      "change": 0.001267,
      "change_pct": 0.1092,
      "direction": "up",
      "price_time": "2026-06-16T13:15:00-04:00",
      "sparkline": [
        1.160362,
        1.160497,
        1.161036,
        1.161305,
        1.16144,
        1.161575,
        1.16117,
        1.160766,
        1.160227,
        1.160227,
        1.159958,
        1.159824,
        1.160497,
        1.160362,
        1.160362,
        1.160093,
        1.160227,
        1.159555,
        1.159824,
        1.15942,
        1.159958,
        1.161036,
        1.160497,
        1.160497,
        1.161036,
        1.16171,
        1.16198,
        1.16198,
        1.16171,
        1.16171,
        1.161575,
        1.161575
      ],
      "status": "ok"
    },
    {
      "symbol": "DX-Y.NYB",
      "name": "DXY",
      "category": "Dólar",
      "price": 99.516998,
      "previous_close": 99.629997,
      "change": -0.112999,
      "change_pct": -0.1134,
      "direction": "down",
      "price_time": "2026-06-16T13:00:00-04:00",
      "sparkline": [
        99.622002,
        99.622002,
        99.616997,
        99.573997,
        99.564003,
        99.540001,
        99.532997,
        99.566002,
        99.593002,
        99.632004,
        99.639,
        99.650002,
        99.664001,
        99.621002,
        99.627998,
        99.628998,
        99.650002,
        99.620003,
        99.664001,
        99.640999,
        99.667,
        99.637001,
        99.556,
        99.598,
        99.595001,
        99.566002,
        99.501999,
        99.482002,
        99.483002,
        99.507004,
        99.512001,
        99.516998
      ],
      "status": "ok"
    },
    {
      "symbol": "^GSPC",
      "name": "S&P 500",
      "category": "Índice",
      "price": 7531.870117,
      "previous_close": 7554.290039,
      "change": -22.419922,
      "change_pct": -0.2968,
      "direction": "down",
      "price_time": "2026-06-16T13:15:00-04:00",
      "sparkline": [
        7573.200195,
        7575.859863,
        7571.029785,
        7570.080078,
        7569.189941,
        7572.529785,
        7568.899902,
        7563.310059,
        7563.339844,
        7558.540039,
        7564.209961,
        7560.930176,
        7561.109863,
        7554.799805,
        7555.089844,
        7555.259766,
        7558.879883,
        7550.560059,
        7558.200195,
        7541.810059,
        7544.370117,
        7539.490234,
        7544.700195,
        7536.660156,
        7534.810059,
        7537.97998,
        7547.140137,
        7544.069824,
        7540.759766,
        7537.439941,
        7536.160156,
        7531.870117
      ],
      "status": "ok"
    },
    {
      "symbol": "^IXIC",
      "name": "Nasdaq",
      "category": "Índice",
      "price": 26536.738281,
      "previous_close": 26683.939453,
      "change": -147.201172,
      "change_pct": -0.5516,
      "direction": "down",
      "price_time": "2026-06-16T13:15:00-04:00",
      "sparkline": [
        26662.347656,
        26680.269531,
        26654.033203,
        26647.449219,
        26651.167969,
        26676.044922,
        26676.251953,
        26669.402344,
        26654.849609,
        26645.441406,
        26665.722656,
        26661.869141,
        26640.525391,
        26619.226562,
        26651.765625,
        26686.636719,
        26703.892578,
        26730.671875,
        26722.144531,
        26595.640625,
        26602.816406,
        26571.142578,
        26611.947266,
        26562.179688,
        26525.769531,
        26527.232422,
        26577.417969,
        26581.636719,
        26553.505859,
        26554.724609,
        26546.492188,
        26536.738281
      ],
      "status": "ok"
    },
    {
      "symbol": "^DJI",
      "name": "Dow Jones",
      "category": "Índice",
      "price": 52138.179688,
      "previous_close": 51671.03125,
      "change": 467.148438,
      "change_pct": 0.9041,
      "direction": "up",
      "price_time": "2026-06-16T13:15:00-04:00",
      "sparkline": [
        51911.191406,
        51936.191406,
        51884.28125,
        51905.191406,
        51912.140625,
        51919.710938,
        51876.660156,
        51839.5,
        51828.398438,
        51784.441406,
        51800.941406,
        51785.808594,
        51811.589844,
        51766.148438,
        51753.121094,
        51692.121094,
        52020.378906,
        51908.679688,
        52054.210938,
        51985.488281,
        51957.171875,
        52016.46875,
        52011.710938,
        52053.488281,
        52077.261719,
        52121.0,
        52179.878906,
        52154.390625,
        52173.96875,
        52161.070312,
        52176.039062,
        52138.179688
      ],
      "status": "ok"
    },
    {
      "symbol": "^VIX",
      "name": "VIX",
      "category": "Volatilidad",
      "price": 15.98,
      "previous_close": 16.200001,
      "change": -0.220001,
      "change_pct": -1.358,
      "direction": "down",
      "price_time": "2026-06-16T13:00:00-04:00",
      "sparkline": [
        16.110001,
        16.15,
        16.16,
        16.16,
        16.18,
        16.18,
        16.17,
        16.16,
        16.15,
        16.139999,
        16.139999,
        16.08,
        16.139999,
        16.129999,
        16.08,
        16.110001,
        16.08,
        16.030001,
        15.97,
        15.81,
        16.08,
        15.98,
        15.99,
        15.83,
        15.96,
        15.98,
        15.95,
        15.84,
        15.88,
        15.88,
        15.99,
        15.98
      ],
      "status": "ok"
    },
    {
      "symbol": "^TNX",
      "name": "US 10Y",
      "category": "Tasa",
      "price": 4.426,
      "previous_close": 4.487,
      "change": -0.061,
      "change_pct": -1.3595,
      "direction": "down",
      "price_time": "2026-06-16T13:05:00-04:00",
      "sparkline": [
        4.461,
        4.463,
        4.465,
        4.471,
        4.469,
        4.467,
        4.469,
        4.469,
        4.471,
        4.471,
        4.469,
        4.469,
        4.445,
        4.438,
        4.443,
        4.449,
        4.451,
        4.457,
        4.453,
        4.453,
        4.451,
        4.451,
        4.447,
        4.445,
        4.441,
        4.441,
        4.432,
        4.426,
        4.428,
        4.428,
        4.426,
        4.426
      ],
      "status": "ok"
    },
    {
      "symbol": "GC=F",
      "name": "Oro",
      "category": "Commodity",
      "price": 4361.0,
      "previous_close": 4328.0,
      "change": 33.0,
      "change_pct": 0.7625,
      "direction": "up",
      "price_time": "2026-06-16T13:00:00-04:00",
      "sparkline": [
        4361.0,
        4362.799805,
        4366.200195,
        4366.799805,
        4365.399902,
        4367.700195,
        4369.899902,
        4362.700195,
        4363.200195,
        4359.600098,
        4361.399902,
        4365.399902,
        4364.600098,
        4370.899902,
        4375.899902,
        4364.700195,
        4356.200195,
        4359.899902,
        4352.700195,
        4356.600098,
        4340.5,
        4345.100098,
        4344.399902,
        4345.100098,
        4346.700195,
        4347.299805,
        4355.700195,
        4366.700195,
        4365.700195,
        4365.0,
        4361.799805,
        4361.0
      ],
      "status": "ok"
    },
    {
      "symbol": "CL=F",
      "name": "WTI",
      "category": "Commodity",
      "price": 75.150002,
      "previous_close": 80.75,
      "change": -5.599998,
      "change_pct": -6.935,
      "direction": "down",
      "price_time": "2026-06-16T13:00:00-04:00",
      "sparkline": [
        77.709999,
        77.849998,
        77.769997,
        77.559998,
        77.43,
        77.160004,
        77.300003,
        77.260002,
        77.18,
        77.349998,
        77.279999,
        76.730003,
        76.510002,
        76.199997,
        76.419998,
        76.660004,
        76.699997,
        77.040001,
        76.860001,
        76.93,
        76.57,
        76.220001,
        76.290001,
        76.400002,
        76.129997,
        75.809998,
        75.209999,
        75.18,
        75.040001,
        74.900002,
        74.980003,
        75.150002
      ],
      "status": "ok"
    },
    {
      "symbol": "HG=F",
      "name": "Cobre",
      "category": "Commodity",
      "price": 6.494,
      "previous_close": 6.4825,
      "change": 0.0115,
      "change_pct": 0.1774,
      "direction": "up",
      "price_time": "2026-06-16T13:00:00-04:00",
      "sparkline": [
        6.487,
        6.4815,
        6.4845,
        6.487,
        6.485,
        6.4915,
        6.498,
        6.4965,
        6.4995,
        6.5025,
        6.5045,
        6.492,
        6.4905,
        6.497,
        6.5005,
        6.5195,
        6.51,
        6.5195,
        6.522,
        6.532,
        6.4985,
        6.5055,
        6.5095,
        6.5185,
        6.522,
        6.5125,
        6.5045,
        6.513,
        6.508,
        6.5085,
        6.502,
        6.494
      ],
      "status": "ok"
    },
    {
      "symbol": "BTC-USD",
      "name": "Bitcoin",
      "category": "Crypto",
      "price": 65731.03125,
      "previous_close": 66289.5,
      "change": -558.46875,
      "change_pct": -0.8425,
      "direction": "down",
      "price_time": "2026-06-16T13:15:00-04:00",
      "sparkline": [
        66652.007812,
        66461.648438,
        66500.15625,
        66625.0625,
        66567.507812,
        66456.898438,
        66464.25,
        66428.71875,
        66361.492188,
        66440.492188,
        66497.898438,
        66532.820312,
        66444.117188,
        66367.976562,
        66155.976562,
        65956.960938,
        66076.851562,
        65997.992188,
        65979.820312,
        65513.898438,
        65635.242188,
        65604.09375,
        65809.101562,
        65761.78125,
        65787.992188,
        65811.398438,
        65710.640625,
        65727.382812,
        65745.476562,
        65694.34375,
        65723.570312,
        65731.03125
      ],
      "status": "ok"
    }
  ],
  "errors": [],
  "disclaimer": "Data referencial obtenida mediante yfinance/Yahoo Finance. No usar como fuente oficial de trading, contabilidad o reporting regulatorio."
}