{
  "source": "yfinance",
  "fetched_at_utc": "2026-07-22T00:04:10.461027+00:00",
  "fetched_at_lima": "2026-07-21T19:04:10.461027-05:00",
  "interval": "15m",
  "period": "5d",
  "count": 12,
  "ok_count": 12,
  "error_count": 0,
  "data": [
    {
      "symbol": "USDPEN=X",
      "name": "USD/PEN",
      "category": "FX",
      "price": 3.3948,
      "previous_close": 3.320709,
      "change": 0.074091,
      "change_pct": 2.2312,
      "direction": "up",
      "price_time": "2026-07-21T19:45:00-04:00",
      "sparkline": [
        3.3943,
        3.3952,
        3.3947,
        3.3948,
        3.3977,
        3.3939,
        3.3942,
        3.394,
        3.3946,
        3.3942,
        3.3953,
        3.3942,
        3.3962,
        3.3968,
        3.3956,
        3.3983,
        3.3953,
        3.3943,
        3.394,
        3.3942,
        3.394,
        3.3946,
        3.3941,
        3.3956,
        3.3985,
        3.3985,
        3.3948,
        3.3973,
        3.3947,
        3.3948,
        3.3948,
        3.3948
      ],
      "status": "ok"
    },
    {
      "symbol": "EURUSD=X",
      "name": "EUR/USD",
      "category": "FX",
      "price": 1.140641,
      "previous_close": 1.141813,
      "change": -0.001172,
      "change_pct": -0.1026,
      "direction": "down",
      "price_time": "2026-07-21T20:00:00-04:00",
      "sparkline": [
        1.141162,
        1.141422,
        1.141162,
        1.141292,
        1.141292,
        1.141032,
        1.141032,
        1.140511,
        1.140511,
        1.140511,
        1.140641,
        1.140381,
        1.140641,
        1.140511,
        1.140381,
        1.140511,
        1.140381,
        1.140381,
        1.140121,
        1.140251,
        1.140251,
        1.140511,
        1.140641,
        1.140251,
        1.140381,
        1.140381,
        1.140251,
        1.140251,
        1.140251,
        1.140381,
        1.140511,
        1.140641
      ],
      "status": "ok"
    },
    {
      "symbol": "DX-Y.NYB",
      "name": "DXY",
      "category": "Dólar",
      "price": 101.182999,
      "previous_close": 100.989998,
      "change": 0.193001,
      "change_pct": 0.1911,
      "direction": "up",
      "price_time": "2026-07-21T19:45:00-04:00",
      "sparkline": [
        101.112999,
        101.138,
        101.136002,
        101.109001,
        101.133003,
        101.128998,
        101.128998,
        101.123001,
        101.102997,
        101.115997,
        101.115997,
        101.099998,
        101.120003,
        101.129997,
        101.18,
        101.171997,
        101.188004,
        101.172997,
        101.181999,
        101.166,
        101.185997,
        101.179001,
        101.185997,
        101.184998,
        101.186996,
        101.203003,
        101.194,
        101.195999,
        101.181,
        101.185997,
        101.192001,
        101.182999
      ],
      "status": "ok"
    },
    {
      "symbol": "^GSPC",
      "name": "S&P 500",
      "category": "Índice",
      "price": 7507.319824,
      "previous_close": 7443.279785,
      "change": 64.040039,
      "change_pct": 0.8604,
      "direction": "up",
      "price_time": "2026-07-21T15:45:00-04:00",
      "sparkline": [
        7450.799805,
        7452.870117,
        7442.830078,
        7452.140137,
        7454.689941,
        7444.72998,
        7470.75,
        7478.629883,
        7482.149902,
        7493.799805,
        7491.169922,
        7492.720215,
        7497.490234,
        7504.720215,
        7501.25,
        7499.52002,
        7507.399902,
        7511.470215,
        7511.52002,
        7511.779785,
        7511.890137,
        7509.339844,
        7511.97998,
        7511.529785,
        7507.470215,
        7507.450195,
        7510.970215,
        7509.040039,
        7507.759766,
        7507.660156,
        7510.709961,
        7507.319824
      ],
      "status": "ok"
    },
    {
      "symbol": "^IXIC",
      "name": "Nasdaq",
      "category": "Índice",
      "price": 25829.607422,
      "previous_close": 25508.070312,
      "change": 321.537109,
      "change_pct": 1.2605,
      "direction": "up",
      "price_time": "2026-07-21T15:45:00-04:00",
      "sparkline": [
        25556.214844,
        25568.369141,
        25533.783203,
        25565.759766,
        25573.929688,
        25510.265625,
        25713.119141,
        25716.734375,
        25722.769531,
        25781.923828,
        25786.099609,
        25793.277344,
        25828.207031,
        25844.607422,
        25824.220703,
        25817.685547,
        25840.585938,
        25838.775391,
        25839.136719,
        25857.501953,
        25861.228516,
        25855.207031,
        25861.833984,
        25863.574219,
        25858.039062,
        25847.332031,
        25866.107422,
        25841.058594,
        25829.626953,
        25823.574219,
        25846.226562,
        25829.607422
      ],
      "status": "ok"
    },
    {
      "symbol": "^DJI",
      "name": "Dow Jones",
      "category": "Índice",
      "price": 52221.378906,
      "previous_close": 51839.261719,
      "change": 382.117188,
      "change_pct": 0.7371,
      "direction": "up",
      "price_time": "2026-07-21T15:45:00-04:00",
      "sparkline": [
        51831.828125,
        51851.238281,
        51799.460938,
        51857.828125,
        51881.988281,
        51851.710938,
        51903.210938,
        52014.550781,
        52165.78125,
        52180.761719,
        52104.46875,
        52106.371094,
        52132.789062,
        52190.511719,
        52204.398438,
        52205.179688,
        52253.089844,
        52324.039062,
        52340.140625,
        52346.679688,
        52316.148438,
        52277.390625,
        52275.808594,
        52250.25,
        52201.371094,
        52225.789062,
        52214.308594,
        52210.578125,
        52219.878906,
        52236.441406,
        52215.921875,
        52221.378906
      ],
      "status": "ok"
    },
    {
      "symbol": "^VIX",
      "name": "VIX",
      "category": "Volatilidad",
      "price": 17.049999,
      "previous_close": 18.65,
      "change": -1.6,
      "change_pct": -8.5791,
      "direction": "down",
      "price_time": "2026-07-21T16:00:00-04:00",
      "sparkline": [
        17.879999,
        17.93,
        17.809999,
        17.82,
        17.75,
        17.98,
        17.76,
        17.639999,
        17.4,
        17.43,
        17.360001,
        17.23,
        17.120001,
        17.209999,
        17.26,
        17.139999,
        17.07,
        17.110001,
        17.1,
        17.08,
        17.1,
        17.049999,
        17.02,
        17.120001,
        17.1,
        17.02,
        17.0,
        17.01,
        17.0,
        16.92,
        16.91,
        17.049999
      ],
      "status": "ok"
    },
    {
      "symbol": "^TNX",
      "name": "US 10Y",
      "category": "Tasa",
      "price": 4.628,
      "previous_close": 4.598,
      "change": 0.03,
      "change_pct": 0.6525,
      "direction": "up",
      "price_time": "2026-07-21T14:50:00-04:00",
      "sparkline": [
        4.6,
        4.598,
        4.6,
        4.598,
        4.598,
        4.602,
        4.604,
        4.606,
        4.61,
        4.62,
        4.634,
        4.628,
        4.622,
        4.626,
        4.62,
        4.622,
        4.618,
        4.62,
        4.626,
        4.626,
        4.626,
        4.63,
        4.626,
        4.628,
        4.626,
        4.628,
        4.632,
        4.632,
        4.632,
        4.632,
        4.628,
        4.628
      ],
      "status": "ok"
    },
    {
      "symbol": "GC=F",
      "name": "Oro",
      "category": "Commodity",
      "price": 4085.199951,
      "previous_close": 4010.300049,
      "change": 74.899902,
      "change_pct": 1.8677,
      "direction": "up",
      "price_time": "2026-07-21T19:45:00-04:00",
      "sparkline": [
        4077.800049,
        4081.399902,
        4080.199951,
        4078.600098,
        4082.5,
        4080.0,
        4076.199951,
        4075.899902,
        4074.800049,
        4076.699951,
        4072.600098,
        4073.0,
        4075.800049,
        4088.699951,
        4087.300049,
        4087.0,
        4085.300049,
        4088.600098,
        4087.5,
        4088.600098,
        4088.800049,
        4086.899902,
        4085.399902,
        4082.199951,
        4083.199951,
        4086.699951,
        4087.899902,
        4084.600098,
        4085.399902,
        4085.199951,
        4084.899902,
        4085.199951
      ],
      "status": "ok"
    },
    {
      "symbol": "CL=F",
      "name": "WTI",
      "category": "Commodity",
      "price": 84.82,
      "previous_close": 83.230003,
      "change": 1.589996,
      "change_pct": 1.9104,
      "direction": "up",
      "price_time": "2026-07-21T19:45:00-04:00",
      "sparkline": [
        84.199997,
        84.559998,
        84.720001,
        84.510002,
        84.269997,
        84.330002,
        84.470001,
        84.389999,
        84.110001,
        84.199997,
        84.419998,
        84.360001,
        84.190002,
        84.379997,
        84.139999,
        84.510002,
        84.660004,
        84.639999,
        84.650002,
        84.669998,
        84.510002,
        84.510002,
        84.379997,
        84.540001,
        84.650002,
        84.660004,
        84.739998,
        84.709999,
        84.720001,
        84.68,
        84.849998,
        84.82
      ],
      "status": "ok"
    },
    {
      "symbol": "HG=F",
      "name": "Cobre",
      "category": "Commodity",
      "price": 6.5295,
      "previous_close": 6.299,
      "change": 0.2305,
      "change_pct": 3.6593,
      "direction": "up",
      "price_time": "2026-07-21T19:45:00-04:00",
      "sparkline": [
        6.53,
        6.5385,
        6.54,
        6.548,
        6.557,
        6.56,
        6.5615,
        6.55,
        6.5335,
        6.5345,
        6.525,
        6.527,
        6.5235,
        6.527,
        6.526,
        6.5265,
        6.5265,
        6.5275,
        6.5265,
        6.529,
        6.5225,
        6.5245,
        6.5285,
        6.5295,
        6.5315,
        6.5345,
        6.5295,
        6.53,
        6.5305,
        6.532,
        6.5305,
        6.5295
      ],
      "status": "ok"
    },
    {
      "symbol": "BTC-USD",
      "name": "Bitcoin",
      "category": "Crypto",
      "price": 66557.34375,
      "previous_close": 65230.027344,
      "change": 1327.316406,
      "change_pct": 2.0348,
      "direction": "up",
      "price_time": "2026-07-21T20:00:00-04:00",
      "sparkline": [
        66506.726562,
        66528.273438,
        66512.632812,
        66424.992188,
        66416.101562,
        66460.132812,
        66170.421875,
        66253.710938,
        66199.367188,
        66241.007812,
        66282.007812,
        66270.132812,
        66366.617188,
        66436.539062,
        66415.4375,
        66391.671875,
        66359.242188,
        66422.0625,
        66370.007812,
        66365.992188,
        66286.140625,
        66314.132812,
        66346.90625,
        66274.460938,
        66240.359375,
        66276.023438,
        66268.007812,
        66239.617188,
        66363.289062,
        66383.21875,
        66405.007812,
        66557.34375
      ],
      "status": "ok"
    }
  ],
  "errors": [],
  "disclaimer": "Data referencial obtenida mediante yfinance/Yahoo Finance. No usar como fuente oficial de trading, contabilidad o reporting regulatorio."
}