{
  "fuente": "https://www.sbs.gob.pe/app/pp/SISTIP_PORTAL/Paginas/Publicacion/TipoCambioContable.aspx",
  "source_used": "directo",
  "fecha_publicada": "20/04/2026",
  "fecha_iso": "2026-04-20",
  "generado_utc": "2026-04-21T01:08:30.669449+00:00",
  "rows": 42,
  "hash": "cf619eddd68a61d75a87f1c10c631d0750bd4bf66a36a2c08867bc984456118c",
  "data": [
    {
      "pais": "Argentina",
      "moneda": "Peso Argentino",
      "tc": 0.002498
    },
    {
      "pais": "Australia",
      "moneda": "Dólar Australiano",
      "tc": 2.465203
    },
    {
      "pais": "Bolivia, Estado Plurinacional de",
      "moneda": "Boliviano",
      "tc": 0.501123
    },
    {
      "pais": "Brasil",
      "moneda": "Real",
      "tc": 0.690055
    },
    {
      "pais": "Bulgaria",
      "moneda": "Lev",
      "tc": 2.070379
    },
    {
      "pais": "Canadá",
      "moneda": "Dólar Canadiense",
      "tc": 2.518877
    },
    {
      "pais": "Chile",
      "moneda": "Peso Chileno",
      "tc": 0.003896
    },
    {
      "pais": "China",
      "moneda": "Yuan",
      "tc": 0.504027
    },
    {
      "pais": "China",
      "moneda": "Yuan Chino Off-Shore",
      "tc": 0.504144
    },
    {
      "pais": "Colombia",
      "moneda": "Peso Colombiano",
      "tc": 0.000962
    },
    {
      "pais": "Corea, República de (Sur)",
      "moneda": "Won Surcoreano",
      "tc": 0.002333
    },
    {
      "pais": "Costa Rica",
      "moneda": "Colón de Costa Rica",
      "tc": 0.007594
    },
    {
      "pais": "Ecuador",
      "moneda": "Dólar de N.A.",
      "tc": 3.436
    },
    {
      "pais": "Emiratos Árabes Unidos",
      "moneda": "Dirham",
      "tc": 0.935475
    },
    {
      "pais": "Estados Unidos de América",
      "moneda": "Dólar de N.A.",
      "tc": 3.436
    },
    {
      "pais": "Federación Rusa (Rusia)",
      "moneda": "Rublo",
      "tc": 0.046005
    },
    {
      "pais": "Filipinas",
      "moneda": "Peso de Filipinas",
      "tc": 0.057295
    },
    {
      "pais": "Georgia",
      "moneda": "Lari Georgiano",
      "tc": 1.288679
    },
    {
      "pais": "Guatemala",
      "moneda": "Quetzal",
      "tc": 0.449779
    },
    {
      "pais": "Hong Kong",
      "moneda": "Dólar de Hong Kong",
      "tc": 0.438788
    },
    {
      "pais": "India",
      "moneda": "Rupia de la India",
      "tc": 0.036899
    },
    {
      "pais": "Indonesia",
      "moneda": "Rupia de Indonesia",
      "tc": 0.000199
    },
    {
      "pais": "Japón",
      "moneda": "Yen Japonés",
      "tc": 0.021643
    },
    {
      "pais": "Malasia",
      "moneda": "Dólar Malasio o Ringgit",
      "tc": 0.869542
    },
    {
      "pais": "México",
      "moneda": "Peso Mexicano",
      "tc": 0.198426
    },
    {
      "pais": "Namibia",
      "moneda": "Dólar Namibio",
      "tc": 0.209891
    },
    {
      "pais": "Nigeria",
      "moneda": "Naira Nigeriana",
      "tc": 0.00255
    },
    {
      "pais": "Noruega",
      "moneda": "Corona Noruega",
      "tc": 0.368927
    },
    {
      "pais": "Panamá",
      "moneda": "Balboa",
      "tc": 3.436
    },
    {
      "pais": "Paraguay",
      "moneda": "Guaraní",
      "tc": 0.000543
    },
    {
      "pais": "Polonia",
      "moneda": "Zloty Polaco",
      "tc": 0.957105
    },
    {
      "pais": "Reino Unido",
      "moneda": "Libra Esterlina",
      "tc": 4.651416
    },
    {
      "pais": "República Dominicana",
      "moneda": "Peso de República Dominicana",
      "tc": 0.057477
    },
    {
      "pais": "Singapur",
      "moneda": "Dólar de Singapur",
      "tc": 2.7053
    },
    {
      "pais": "Suecia",
      "moneda": "Corona Sueca",
      "tc": 0.376603
    },
    {
      "pais": "Suiza",
      "moneda": "Franco Suizo",
      "tc": 4.414185
    },
    {
      "pais": "Tailandia",
      "moneda": "Baht",
      "tc": 0.107375
    },
    {
      "pais": "Taiwán, Provincia de China",
      "moneda": "Nuevo Dólar de Taiwan",
      "tc": 0.108976
    },
    {
      "pais": "Turquía",
      "moneda": "Lira",
      "tc": 0.076623
    },
    {
      "pais": "Unión",
      "moneda": "Europea Euro",
      "tc": 4.049024
    },
    {
      "pais": "Uruguay",
      "moneda": "Peso Uruguayo",
      "tc": 0.08657
    },
    {
      "pais": "Vietnam",
      "moneda": "Dong",
      "tc": 0.000131
    }
  ]
}